{"monitoring_info.md":"BIrVF8ej","outline_install.md":"Dgpbkub3","outline_member.md":"CVJ-C29O","outline_theme-and-skin.md":"Bojk1sSn","monitoring_helpers_deprecated.md":"CxV2exPx","outline_tip.md":"ijO1wu6I","outline_remove-youngcart.md":"CRJV87AV","outline_basic-config.md":"BU8CPW5T","outline_menu.md":"JX9VkYBv","outline_update.md":"Af1VHqbX","outline_point.md":"COQic2cE","outline_index.md":"CChNfZtN","outline_theme_skin.md":"C2Qa9vDb","outline_board.md":"B0aLl4bJ","outline_upgrade.md":"DfNh2JmR","outline_config.md":"BFiSQ6my","outline_privacy.md":"CMc0ylFX","monitoring_process.md":"CIYjzOgu","index.md":"BLfTOSQ0"}
