{"outline_tip.md":"iO6vI1cZ","outline_config.md":"CdKL-Itf","monitoring_info.md":"DhFGNj08","outline_basic-config.md":"B_slUkq_","outline_install.md":"aeS8rj9N","outline_board.md":"gwkt5Z9n","monitoring_process.md":"CMCjXLKb","outline_member.md":"CveQ1N5G","outline_upgrade.md":"BpzGsWzu","outline_menu.md":"CiRRd_SV","outline_point.md":"CuvCowFu","outline_privacy.md":"BD2aYdpE","outline_index.md":"BX1Iuvk5","outline_remove-youngcart.md":"BU_mKNTU","outline_theme-and-skin.md":"BQY19tOM","outline_update.md":"Dz7KzQZq","monitoring_helpers_deprecated.md":"urhrh9_j","outline_theme_skin.md":"B7ms_sLL","index.md":"DyGE6kyF"}
