{"outline_update.md":"CXMXvsZb","outline_tip.md":"C0nJ-6WD","monitoring_process.md":"BaSraYom","outline_board.md":"BdRTdzJ4","outline_member.md":"DXqdltmP","outline_config.md":"Blzdobse","outline_basic-config.md":"B2chpjvD","outline_point.md":"xfjb3nPm","outline_theme-and-skin.md":"C_EXvbGS","outline_upgrade.md":"CKLN0XQe","outline_install.md":"W6lZ8Ilu","outline_menu.md":"Bbii1kzC","outline_privacy.md":"B2FuGCTz","outline_remove-youngcart.md":"CsLPmCrm","index.md":"f3NCIbJd","monitoring_helpers_deprecated.md":"CFwVyMZz","monitoring_info.md":"CSI5Qvpn","outline_theme_skin.md":"BygBhcVC","outline_index.md":"CDi-f5X5"}
