{"index.md":"CPFeF4bA","outline_theme_skin.md":"DmbeAIbT","outline_privacy.md":"BVkjFJ2Q","outline_board.md":"CSxCT4Q5","outline_remove-youngcart.md":"CC4SmFHG","outline_basic-config.md":"CLFMgNJl","outline_upgrade.md":"CPjROoRK","outline_theme-and-skin.md":"x3of-r4H","outline_member.md":"Co5PhJe4","outline_update.md":"B3midbas","monitoring_helpers_deprecated.md":"C6aNGdFv","outline_menu.md":"8P9ZcRgR","outline_install.md":"BYODEbj4","outline_index.md":"CBpbPfoQ","monitoring_process.md":"CIrdo6zf","outline_point.md":"BU0mU_V9","outline_config.md":"Bs1PrTG1","outline_tip.md":"xCwQLU12","monitoring_info.md":"0qorkJ57"}
