{"monitoring_process.md":"aozqNj-i","outline_board.md":"D5i0mGUf","index.md":"BkAU4jXd","outline_update.md":"DBL3_0xE","outline_basic-config.md":"Bl6KeAqc","monitoring_info.md":"DseDomXN","outline_member.md":"mVPO9mPw","outline_point.md":"BRdRTtij","outline_tip.md":"BAam4x9n","outline_config.md":"B0FHb_Ya","monitoring_helpers_deprecated.md":"DRSd6zjc","outline_theme_skin.md":"Cj7W2P8U","outline_menu.md":"CDnDzVa0","outline_remove-youngcart.md":"CDijJywU","outline_privacy.md":"7ZbcvJH2","outline_upgrade.md":"DyeFC4lu","outline_index.md":"DspwiVDx","outline_theme-and-skin.md":"pwM5JtCr","outline_install.md":"Bt8SxnYd"}
