{"outline_board.md":"D4aWNaUc","outline_tip.md":"DAU5-C_g","monitoring_helpers_deprecated.md":"BgJn7LP3","outline_menu.md":"dchj4r3j","outline_config.md":"DsG12z5a","outline_index.md":"GK3Cd6el","outline_member.md":"DsE84YdE","outline_upgrade.md":"CXaqxWyQ","monitoring_info.md":"x9VsZQzu","outline_privacy.md":"DiKMxLvR","outline_theme_skin.md":"1t4OYTri","outline_basic-config.md":"sCbSX-zU","outline_theme-and-skin.md":"BDIzwjrW","outline_point.md":"DdyeSxUn","outline_install.md":"Zv0m7rs4","outline_remove-youngcart.md":"BqnW1KfE","index.md":"BhdgeUrZ","outline_update.md":"DeYRQ2HX","monitoring_process.md":"DGwDJjAM"}
