{"outline_menu.md":"Cntpt44J","index.md":"CI5CaL26","outline_tip.md":"dNNdmWra","outline_point.md":"DbFrvFpN","monitoring_info.md":"DP7QePY5","outline_member.md":"DU3HMJTw","outline_config.md":"DzacvWb5","outline_index.md":"BEIFhNhm","outline_remove-youngcart.md":"CGi-wACk","outline_install.md":"DZxTU4Lk","outline_theme-and-skin.md":"Dfl1BMrL","outline_privacy.md":"E7t_iGkk","outline_theme_skin.md":"D_H1iaAu","outline_upgrade.md":"aVUQ_yME","monitoring_process.md":"D_rH3uJH","monitoring_helpers_deprecated.md":"CBqIlIdi","outline_basic-config.md":"B4QBRZXi","outline_update.md":"DzAHkq4B","outline_board.md":"1Iu8whUN"}
