{"outline_config.md":"Ca3SWO6S","outline_theme-and-skin.md":"C6HjLuUx","index.md":"MwsnjVM0","outline_update.md":"C2KCd0dr","outline_privacy.md":"CigwKOY6","outline_board.md":"qQM5yPah","outline_remove-youngcart.md":"DGOF0RhA","outline_menu.md":"C9cbf3UP","outline_tip.md":"BJLwVcBH","outline_upgrade.md":"B5O30ZOp","outline_theme_skin.md":"BRLwghPl","outline_basic-config.md":"smwEXIPq","outline_index.md":"DV_d3uak","monitoring_process.md":"OK4MavXb","outline_member.md":"BH_KgopC","monitoring_helpers_deprecated.md":"DXRAwei6","monitoring_info.md":"BXB-mL0W","outline_point.md":"C5uwLkDy","outline_install.md":"CHwy6P5G"}
