{"outline_menu.md":"DYsjlPkt","outline_board.md":"D_jkRV1p","outline_config.md":"KqzqF8cw","outline_theme-and-skin.md":"Cj-GRQzZ","index.md":"CgVq8ii6","monitoring_process.md":"4x3fT_I0","outline_privacy.md":"Dz7KPUrN","outline_tip.md":"HJpWONlP","outline_theme_skin.md":"FxkOSkVN","outline_update.md":"DSXh_OkM","monitoring_info.md":"BlyjVBWP","outline_index.md":"4PsbFoyc","outline_install.md":"DhdOxMxv","outline_member.md":"xFux349p","outline_remove-youngcart.md":"BABtJynd","outline_basic-config.md":"D4bf0H1V","outline_point.md":"D_kVe5sB","outline_upgrade.md":"vtLMzBCK","monitoring_helpers_deprecated.md":"BWvYgsc7"}
