{"outline_index.md":"Ba4Mx147","outline_board.md":"DNqjx9FX","monitoring_process.md":"R188ATts","outline_menu.md":"DHvbx2iO","monitoring_info.md":"DJ7kNFVs","outline_point.md":"SdemBqPe","outline_install.md":"DKHcxvmZ","outline_config.md":"CulYLBKC","outline_update.md":"1YfeYzMY","monitoring_helpers_deprecated.md":"4KWzs4N7","outline_theme-and-skin.md":"D64O91iF","outline_upgrade.md":"CYvmX1Fg","outline_basic-config.md":"DydEhsGB","outline_theme_skin.md":"ClFm6p-6","index.md":"D6PYnSTu","outline_remove-youngcart.md":"5IMQBDYY","outline_privacy.md":"CjpHFr_y","outline_tip.md":"DPWcjpZ1","outline_member.md":"D-cm2920"}
