{"outline_tip.md":"DSwnZC6m","outline_basic-config.md":"cADlk2CN","outline_board.md":"BjuQDfVQ","monitoring_process.md":"Dt04soI2","monitoring_info.md":"xRO0Cxi8","outline_upgrade.md":"BBadAamY","monitoring_helpers_deprecated.md":"BCk_FNbz","outline_index.md":"DwuvJl4C","outline_theme-and-skin.md":"B8hdRhb9","outline_menu.md":"CC3U_1Ea","outline_member.md":"BOG3Gceh","outline_privacy.md":"Rlsabijc","outline_update.md":"Wb9hdk4k","outline_config.md":"DnV2g4MW","outline_install.md":"CtKDZ3Oi","outline_point.md":"C133Nr3T","index.md":"BcPEb5Xc","outline_theme_skin.md":"aKX1kHHc","outline_remove-youngcart.md":"BXt4JEBK"}
