{"outline_board.md":"Dym2VZ8i","outline_update.md":"DpFSJcoT","outline_tip.md":"B1BG-sSI","outline_theme_skin.md":"v43OcEq7","monitoring_helpers_deprecated.md":"DgX0cSGV","outline_member.md":"BSlCjjuU","monitoring_info.md":"B2ZM1bZI","outline_basic-config.md":"BEs7mFri","outline_remove-youngcart.md":"f0w2PV50","outline_install.md":"C2qghJB6","outline_config.md":"CimtfmJP","outline_point.md":"BQ7NDAWH","outline_upgrade.md":"DFJr4dQ0","outline_index.md":"hhKX--Mf","outline_theme-and-skin.md":"Dl-XbbGX","index.md":"CnfbAdiH","outline_privacy.md":"CCdy24Vb","monitoring_process.md":"D161Vzps","outline_menu.md":"DvkJTxr5"}
