{"outline_basic-config.md":"D2P9rMPX","outline_member.md":"Fxl7Egz5","outline_update.md":"CdL6E65C","outline_privacy.md":"3LWoOzAY","outline_board.md":"BKzICuBg","monitoring_process.md":"DsZ5cFTm","index.md":"DTdfKaEK","outline_tip.md":"DXJ0YqDh","monitoring_helpers_deprecated.md":"DXUbrf_W","outline_point.md":"CT98-9oH","outline_theme_skin.md":"RBUIeL9k","outline_theme-and-skin.md":"Cv6EqdqF","outline_upgrade.md":"BQWGtdCw","outline_remove-youngcart.md":"CULlNB4i","monitoring_info.md":"msmbcdvk","outline_menu.md":"BoRyV3jV","outline_config.md":"DiRiMWkm","outline_index.md":"y6a0X4y1","outline_install.md":"DO67L3h_"}
