{"monitoring_helpers_deprecated.md":"CCMKihuj","outline_upgrade.md":"DMbOzVCn","outline_theme-and-skin.md":"CoqW6_Bg","outline_theme_skin.md":"ChsVxc53","outline_tip.md":"CydBUq7Y","outline_update.md":"DHX-AfT3","outline_privacy.md":"oUzrwaM7","outline_config.md":"BY8JzsFh","outline_board.md":"q7R9g3Kl","monitoring_info.md":"DDBLAoZH","index.md":"CR3sO-6A","outline_point.md":"VkUzAcNu","outline_basic-config.md":"CqICm2RG","outline_install.md":"DIXXn3Vt","outline_remove-youngcart.md":"DsiiXkFG","outline_index.md":"DBmZnMRQ","outline_member.md":"AJTRcFd8","monitoring_process.md":"DJJXTNOV","outline_menu.md":"Bp1gfQNv"}
