{"outline_theme_skin.md":"BAclsXgV","outline_theme-and-skin.md":"DGTRzF85","outline_index.md":"D4uwLXwT","outline_remove-youngcart.md":"Di5LyxD8","outline_board.md":"DY5dCdMt","index.md":"CpbnHzjf","outline_basic-config.md":"D9VYmBbk","outline_privacy.md":"CmIPaaWy","outline_update.md":"BkBkkTSv","monitoring_info.md":"BwwEOwoZ","outline_point.md":"DlFVYtrl","outline_tip.md":"BS5QmUDJ","monitoring_helpers_deprecated.md":"BrZDQMoA","outline_install.md":"MvEqDyd8","outline_member.md":"dH8ADQWO","outline_config.md":"Bzv-Lt7Z","outline_upgrade.md":"Cg34Ea98","monitoring_process.md":"DppYzxJJ","outline_menu.md":"Taj0vJtd"}
