{"index.md":"BBobABxF","outline_index.md":"B5U_-sue","outline_install.md":"BJq6-ME9","outline_theme_skin.md":"CRfErPwD","outline_board.md":"uWIcsFyw","outline_member.md":"D8E5glmt","outline_menu.md":"ele4wYEE","outline_point.md":"CoHlwQ7v","outline_theme-and-skin.md":"q3y8Ah5b","monitoring_process.md":"Bw3cP5O3","outline_remove-youngcart.md":"9Di_prx3","outline_config.md":"D5tHPnzF","outline_basic-config.md":"Apnry9HS","monitoring_helpers_deprecated.md":"DKA23Cgi","outline_tip.md":"BqCtm69O","outline_privacy.md":"BVl2Q4nr","outline_update.md":"CUUvhjX2","monitoring_info.md":"CsmVdlbP","outline_upgrade.md":"CBL3MSNO"}
