{"outline_config.md":"yz5FHuyY","outline_point.md":"BviJ6H2O","outline_privacy.md":"Vl5sjmPI","outline_tip.md":"DLj-YNLn","outline_menu.md":"BsNt_KV3","monitoring_process.md":"DRpTOHZS","outline_theme_skin.md":"t3kBLQE5","outline_board.md":"CtDTFKnZ","outline_update.md":"B5u8sF2U","outline_member.md":"D-p8gfgl","monitoring_info.md":"BvNd64aj","outline_index.md":"B4a7tZFW","outline_theme-and-skin.md":"V462pzDW","outline_install.md":"ViMNzRUV","index.md":"B7ljDCNL","outline_basic-config.md":"DfXKaB14","outline_remove-youngcart.md":"C0pDtqgv","outline_upgrade.md":"Czignn4g","monitoring_helpers_deprecated.md":"CCNJR06O"}
