{"outline_update.md":"Bufh4BP4","outline_basic-config.md":"DQbo3_ZO","outline_board.md":"kbzhja4Y","outline_index.md":"BQ8e6yHY","outline_config.md":"C2QZP6Vk","monitoring_helpers_deprecated.md":"DMiFj33_","monitoring_info.md":"DD2wi3NA","monitoring_process.md":"CoFtvl-T","outline_privacy.md":"DXt37I48","outline_remove-youngcart.md":"DJr1K4XV","outline_theme_skin.md":"DI6NWZyd","outline_tip.md":"ByHai3v8","outline_upgrade.md":"C-kFNzHH","outline_point.md":"BiwIvZxI","outline_member.md":"BVaC7j8d","outline_install.md":"CN-io-75","outline_menu.md":"Se1kH6lL","outline_theme-and-skin.md":"DjMY55yf","index.md":"DOEKnrmb"}
