{"outline_basic-config.md":"Br8j8x-T","outline_index.md":"C_e2AzSU","outline_update.md":"B77ALvOv","outline_menu.md":"T4I-NB95","outline_upgrade.md":"Df2109iE","outline_theme_skin.md":"sZQd28oV","monitoring_helpers_deprecated.md":"CdZu-yjr","outline_privacy.md":"4GAr-h4r","monitoring_info.md":"DJfqTtuO","outline_point.md":"h-PXkUfE","monitoring_process.md":"De31DUnu","index.md":"DN8QGyp-","outline_config.md":"B1e8Hzko","outline_tip.md":"bTsjs8sR","outline_member.md":"BftRNY2W","outline_board.md":"dP7goc34","outline_remove-youngcart.md":"Dp_1svkO","outline_theme-and-skin.md":"B0szTES_","outline_install.md":"CC41kRV7"}
