{"outline_member.md":"BXYKdZMf","outline_basic-config.md":"B-nJUKxX","outline_install.md":"BSYpixu0","monitoring_process.md":"CjqDknUg","outline_tip.md":"lzYDoTpY","outline_upgrade.md":"DWAngH8Z","outline_index.md":"LGtOmCNk","outline_privacy.md":"BXZAKlMF","index.md":"CzK8CMU0","monitoring_info.md":"HBDTckHW","outline_theme-and-skin.md":"BT7nOVL5","outline_update.md":"DeLa3E8y","outline_theme_skin.md":"CthKPdr7","outline_remove-youngcart.md":"DjAPsQZT","outline_config.md":"Bz_BQd8Q","outline_point.md":"z5svFtVL","outline_board.md":"DGUm20We","outline_menu.md":"CRN9EXG9","monitoring_helpers_deprecated.md":"BqItiHiK"}
