{"outline_privacy.md":"DGAXbXxF","outline_install.md":"eICOWFN_","outline_basic-config.md":"BQ1gcC-j","outline_theme_skin.md":"DJXDQUL2","outline_board.md":"DyNEVNYp","outline_update.md":"x_VWcR_I","outline_remove-youngcart.md":"B2QnSodz","outline_tip.md":"BWQ2bMRP","outline_upgrade.md":"DMUX2nAa","monitoring_helpers_deprecated.md":"DRjhf6t6","outline_point.md":"CaYE47vp","outline_menu.md":"T30MDTHz","outline_config.md":"CV210CW9","monitoring_process.md":"Va3oYkyB","index.md":"DvF6d3kC","outline_index.md":"BOwFoUHb","outline_member.md":"DXZ9pMQe","monitoring_info.md":"C3YkRCZw","outline_theme-and-skin.md":"C5Qh5kWt"}
