{"outline_basic-config.md":"_ukugTP9","outline_index.md":"IP5bIAnW","outline_theme-and-skin.md":"CfSLSqYd","monitoring_helpers_deprecated.md":"C8ugnYkc","monitoring_process.md":"hgpMcH_h","outline_point.md":"4mEze7q9","outline_privacy.md":"BsUnw5RO","outline_member.md":"CPICRubc","outline_update.md":"C_HyISFv","outline_install.md":"D-zEMNa5","outline_board.md":"BU4UZsxW","index.md":"Br3Q-hmT","outline_upgrade.md":"C3u-Ddfk","outline_theme_skin.md":"DY4psJTB","outline_tip.md":"MPwz4dao","outline_remove-youngcart.md":"BUGI6dct","outline_config.md":"B4HJbVxC","monitoring_info.md":"BMxXHWod","outline_menu.md":"BNfDgM5d"}
