{"outline_point.md":"BqqZdp7r","outline_member.md":"sJ9_xHLc","outline_index.md":"Cy7pMxCT","outline_upgrade.md":"BpD-Q3kv","index.md":"pbHoMrhm","outline_privacy.md":"hM9CCPSF","outline_board.md":"BD_gtWjV","outline_basic-config.md":"BrM4Je2m","outline_tip.md":"DcYbTE-H","outline_config.md":"BA4HGiz8","outline_menu.md":"BbzjI4R3","outline_update.md":"b3-vhlCw","outline_install.md":"TQEX-uTW","monitoring_process.md":"DqraaMEM","monitoring_info.md":"Ccpq5DR4","monitoring_helpers_deprecated.md":"DMBCBsg2","outline_remove-youngcart.md":"B14wJIla","outline_theme_skin.md":"BBpJG9N7","outline_theme-and-skin.md":"DFGCAIq2"}
