{"outline_index.md":"Bugd6zg0","monitoring_info.md":"HHDX3EEO","monitoring_helpers_deprecated.md":"CGklSIYe","outline_theme_skin.md":"C79-n68v","monitoring_process.md":"DK2hUcLv","outline_member.md":"DEL7Xs0m","outline_tip.md":"CwRM75zp","outline_install.md":"CXAha-5f","outline_board.md":"DUAXWzUS","outline_config.md":"CmKJ7VnK","outline_basic-config.md":"4Btdq2YY","outline_theme-and-skin.md":"B2eMu9PQ","outline_menu.md":"DeRdfp1_","index.md":"DkYLoNQE","outline_remove-youngcart.md":"ZDRwjJml","outline_privacy.md":"CMoI6_65","outline_point.md":"yIJvFPQT","outline_upgrade.md":"nssuy_6i","outline_update.md":"B5LQe0OL"}
