{"outline_tip.md":"DcdtC5fr","outline_point.md":"CbemMR4O","outline_update.md":"DOu1MyjT","outline_upgrade.md":"BSHPexfd","outline_basic-config.md":"CEl56wxI","outline_index.md":"CkWOE8ws","outline_config.md":"KJY1tByD","outline_board.md":"DNTUCYw5","outline_install.md":"FYCsy-yY","outline_member.md":"BvN2GrBN","outline_menu.md":"CJ9vOUAa","outline_privacy.md":"Cqqtzj8S","outline_remove-youngcart.md":"kJAkJ6uA","outline_theme_skin.md":"BOoMASw0","monitoring_helpers_deprecated.md":"cYwMkDmr","monitoring_info.md":"BRi_EX4D","index.md":"WtxodKio","outline_theme-and-skin.md":"DGMTsLKq","monitoring_process.md":"CNEpxRuA"}
