{"monitoring_helpers_deprecated.md":"Co6N_RjL","monitoring_info.md":"KHDgkoBU","outline_basic-config.md":"CrZ1QMux","outline_point.md":"DrAnY7hr","outline_config.md":"B8o2IT8H","index.md":"DKZVSOVm","outline_install.md":"Df90VVHa","outline_menu.md":"oITNs2Zb","outline_privacy.md":"tubdsZYO","outline_board.md":"C42pD64P","outline_member.md":"8f2mEbKQ","monitoring_process.md":"BmvMclJ2","outline_theme-and-skin.md":"DUe1CrPf","outline_theme_skin.md":"DYFyKUux","outline_tip.md":"B32VNFIv","outline_upgrade.md":"1gRrFHrs","outline_index.md":"DtgdIdE2","outline_remove-youngcart.md":"Bs7bWNF_","outline_update.md":"9CdLIaEw"}
