{"index.md":"D-_p77Pg","outline_theme-and-skin.md":"a5G5wSlL","outline_theme_skin.md":"CYkhu2Tn","outline_tip.md":"Fannle0_","outline_update.md":"DOfmJKTE","outline_point.md":"CxuSkBJi","outline_menu.md":"DN4fxwZW","outline_privacy.md":"DLp4lZAu","outline_upgrade.md":"CEz56ng5","outline_remove-youngcart.md":"LFAf82oB","outline_basic-config.md":"DNw61BWQ","outline_member.md":"BIm91wwI","monitoring_process.md":"Cym2Mzgl","monitoring_helpers_deprecated.md":"sbdOFEiX","outline_board.md":"QWTCW_lW","monitoring_info.md":"B1wSh8FJ","outline_config.md":"_4nr1Hrf","outline_install.md":"DJ6dnBoF","outline_index.md":"Bi9mF6xa"}
