{"outline_point.md":"v03KwxR0","outline_theme-and-skin.md":"DdHE4PQ0","outline_remove-youngcart.md":"C9SXdpHY","monitoring_helpers_deprecated.md":"BPkf3-vR","index.md":"1IFoMDQO","outline_theme_skin.md":"C0BeyOeE","outline_tip.md":"BdlrMaL3","outline_update.md":"DIgD71YP","outline_upgrade.md":"BgnH-nOL","outline_board.md":"D4AfVFrJ","outline_privacy.md":"DbregJx3","monitoring_process.md":"BJn3AeUV","monitoring_info.md":"DPQb1tSp","outline_basic-config.md":"9Q72i5wk","outline_member.md":"DKvIaBz0","outline_config.md":"BjRjFilx","outline_index.md":"C8YhCW_-","outline_install.md":"BfkSKDuq","outline_menu.md":"BnZbSgso"}
