{"outline_theme_skin.md":"B5ynfOkr","monitoring_process.md":"DYPKiLUX","outline_index.md":"B-COKGwT","monitoring_info.md":"TFVWXMOL","outline_tip.md":"D7kylWSN","index.md":"DZlE13e5","outline_remove-youngcart.md":"JfgCqjQq","outline_theme-and-skin.md":"B6Nake3X","monitoring_helpers_deprecated.md":"CJKF6bes","outline_board.md":"DXfRi80r","outline_config.md":"HyHapHcX","outline_install.md":"CEhxVzf_","outline_privacy.md":"CGBsXiWc","outline_update.md":"D3AH021r","outline_upgrade.md":"PzR5CUxu","outline_menu.md":"B_FtGrOC","outline_basic-config.md":"BO0TxkNV","outline_point.md":"CJAlKOgG","outline_member.md":"dkOrCDjN"}
