{"monitoring_process.md":"DZ_oZot6","outline_privacy.md":"lJsD5q1m","outline_install.md":"DIbu1K_i","monitoring_info.md":"DiYhSONv","outline_index.md":"Ca-uKMZe","outline_config.md":"D_NOFYEG","outline_remove-youngcart.md":"nWrWUGvR","outline_theme_skin.md":"Cy1SxZXl","outline_update.md":"hYdewj0g","monitoring_helpers_deprecated.md":"Cw6uuMJS","outline_tip.md":"CjBaT3bX","outline_upgrade.md":"DvLTl1CN","outline_member.md":"BK8f3VG0","outline_menu.md":"Cgn9lN6s","outline_board.md":"C4uxB5Wm","outline_basic-config.md":"CPYuHh1B","outline_theme-and-skin.md":"DlakIxm9","index.md":"qamwmhO1","outline_point.md":"aGU4Vp0N"}
