{"outline_install.md":"CF-09N6O","outline_remove-youngcart.md":"BM1h27G7","outline_member.md":"BNPpKBl9","monitoring_process.md":"B-rg9udL","outline_update.md":"Dy7be0Tp","monitoring_helpers_deprecated.md":"D7Ey6RcR","outline_basic-config.md":"EBOcCazk","outline_board.md":"BWCz5QFA","outline_index.md":"CR3h6z0o","outline_config.md":"B51ik4xz","monitoring_info.md":"BSO7ZuFO","outline_upgrade.md":"BgUS0hIN","outline_menu.md":"vpJcDfdF","outline_point.md":"DRnaqHyU","outline_privacy.md":"SFRq1uc2","outline_theme-and-skin.md":"CJsQLyr7","index.md":"CWDxy6mu","outline_theme_skin.md":"Eyj5nWU6","outline_tip.md":"Dj43xph6"}
