{"outline_index.md":"BZMf2iqa","outline_menu.md":"BIOWfSBh","outline_board.md":"BIK5euu1","outline_privacy.md":"DJhDnJjA","index.md":"D68Y1k7C","outline_member.md":"Cv9jQrcB","outline_upgrade.md":"AhdjB68j","monitoring_process.md":"CdoazxCI","outline_basic-config.md":"Cf8dz5bi","outline_theme_skin.md":"CdJjYUpR","monitoring_helpers_deprecated.md":"CmnPVTZO","monitoring_info.md":"CEpVoRxh","outline_point.md":"BoiEdzwj","outline_tip.md":"CWq1F_k2","outline_config.md":"MiSMW11K","outline_theme-and-skin.md":"qX-KhyDC","outline_remove-youngcart.md":"CqFBCzbk","outline_update.md":"l7tOcxGI","outline_install.md":"32vCWtVd"}
