{"outline_index.md":"DLu3FZl7","index.md":"DrvtZXSI","outline_basic-config.md":"n09MCx2W","outline_privacy.md":"DD-RAWDJ","monitoring_info.md":"CZh9R_HW","outline_point.md":"C609t5bN","outline_menu.md":"DjROBEi5","outline_board.md":"CFS68209","monitoring_helpers_deprecated.md":"COOWtAPn","outline_member.md":"DoVmctv-","outline_config.md":"BMq2nYuM","outline_install.md":"CM-Y1dmf","outline_theme-and-skin.md":"BNrEEqOT","outline_tip.md":"CC-mz3Xj","outline_update.md":"BathYuSy","outline_upgrade.md":"CVyyMzza","outline_theme_skin.md":"Cg7eLzZ2","monitoring_process.md":"DXd8bvgG","outline_remove-youngcart.md":"E3RvWQ0K"}
