{"outline_theme_skin.md":"CyD4BIaV","outline_board.md":"FXzbrTSV","outline_update.md":"D6WsaaZN","outline_remove-youngcart.md":"DMBB5bUU","outline_tip.md":"Xbjs65rt","index.md":"ChcW5xsW","outline_install.md":"DXhYHOEy","outline_config.md":"Z4HFm_Gd","outline_index.md":"B9a2eulX","outline_menu.md":"GrP8oYlZ","outline_privacy.md":"pUbcKA6e","monitoring_process.md":"CZk0BtDD","outline_point.md":"DEWFOU5N","outline_member.md":"Q5wOqJVp","outline_theme-and-skin.md":"CJFRsCJv","monitoring_info.md":"C1OFmkl4","outline_basic-config.md":"faSCqyLq","outline_upgrade.md":"DQd1UKhw","monitoring_helpers_deprecated.md":"B35_G4KM"}
