{"monitoring_helpers_deprecated.md":"B_x_RAq8","outline_config.md":"Bp91Q2gh","outline_theme_skin.md":"5FujrcbW","outline_board.md":"CS-hjUUN","outline_update.md":"3VPh4zEC","outline_upgrade.md":"Bid8LtAM","outline_point.md":"6eBnAzXc","outline_index.md":"BVaEVo2l","index.md":"C0s93C0M","outline_member.md":"CcCTAPt6","outline_theme-and-skin.md":"i8n7yKxI","monitoring_process.md":"ByWSFOg3","outline_menu.md":"DWfaOFoX","outline_basic-config.md":"C4a8rP-3","outline_tip.md":"CBQZVlCQ","outline_install.md":"m3ByrAD4","outline_privacy.md":"CZ3NZUrH","monitoring_info.md":"DrmzWeiQ","outline_remove-youngcart.md":"BjP7yw95"}
