{"monitoring_info.md":"DLociTpV","outline_theme_skin.md":"CexPgs0s","monitoring_helpers_deprecated.md":"TZbbu6VA","outline_update.md":"CyCDfjUB","outline_member.md":"BklA7Tcv","outline_privacy.md":"DR0c4ywD","outline_install.md":"CYaLUzhc","outline_basic-config.md":"D51SonHo","monitoring_process.md":"BzMgH4XW","index.md":"D2NISblB","outline_tip.md":"CvcaDw9f","outline_theme-and-skin.md":"JyPxNzF1","outline_upgrade.md":"CJqvBadU","outline_point.md":"5MR8GVv5","outline_menu.md":"CvozBEU6","outline_config.md":"BFH9Baui","outline_index.md":"CTscFAOU","outline_board.md":"BS-OaUtd","outline_remove-youngcart.md":"Bb-GD6xP"}
