{"monitoring_helpers_deprecated.md":"BhX7CEbH","outline_board.md":"CJlfaROx","outline_tip.md":"ZvUcV8Ke","outline_member.md":"nEzwZWb-","index.md":"yJQWO2wu","outline_basic-config.md":"BYo2TaT1","outline_config.md":"D7-uXJF7","outline_theme_skin.md":"Cf9lfKmt","outline_remove-youngcart.md":"CIympseu","outline_install.md":"fXpiT2k0","monitoring_info.md":"DyEL8Tjv","monitoring_process.md":"kGcl2BwK","outline_privacy.md":"BcGBJlEH","outline_upgrade.md":"Ds0rRiAs","outline_theme-and-skin.md":"Cn2s8e1Z","outline_index.md":"CHP5SQIu","outline_menu.md":"CXA12_TO","outline_update.md":"Dn-GuJtX","outline_point.md":"78J2vWRb"}
