{"outline_update.md":"C7m-pCCC","outline_tip.md":"BX4xoRK9","outline_upgrade.md":"DSTsaX0m","outline_board.md":"CuzgQL-C","outline_basic-config.md":"YXaccptw","outline_point.md":"CMbSZ8Eb","outline_member.md":"Ck2d7RaK","outline_install.md":"DI1oYeGP","outline_privacy.md":"DDQ50ZjV","outline_theme_skin.md":"BbuhrJil","outline_menu.md":"b-G0QDz3","index.md":"BpXW_j9-","outline_remove-youngcart.md":"ChkJzB5z","monitoring_helpers_deprecated.md":"DKEces27","monitoring_info.md":"D5v98dWx","monitoring_process.md":"DsR-ljar","outline_index.md":"D5mG608S","outline_config.md":"BjAtB5XO","outline_theme-and-skin.md":"BMayACiD"}
