{"outline_menu.md":"zBHw0ICb","outline_index.md":"B-MqAvmA","outline_member.md":"CECXx4eZ","outline_basic-config.md":"GFJkBKtG","outline_install.md":"CHFhtwIe","outline_theme_skin.md":"Gr3i6aym","outline_remove-youngcart.md":"BVRquvXs","outline_board.md":"eNLs11Nu","index.md":"ChahkGE6","outline_upgrade.md":"Cj0I7HZr","outline_point.md":"7gcyjCnK","outline_privacy.md":"1caoMKEJ","outline_config.md":"DB1EMqkw","outline_tip.md":"C00BKJY_","monitoring_info.md":"OC4zQCH4","monitoring_process.md":"BF7LysbT","monitoring_helpers_deprecated.md":"CZdbrgUl","outline_theme-and-skin.md":"xkV1TKil","outline_update.md":"NabZFMC4"}
