{"outline_basic-config.md":"BMlYToGu","index.md":"DnLhMZDN","monitoring_process.md":"B1B6KG2p","outline_config.md":"TpdYiI_z","outline_theme-and-skin.md":"CeREydUI","outline_board.md":"YMZ03cMM","outline_update.md":"BFbaVcfy","outline_privacy.md":"CTCRTH94","outline_point.md":"B4RdgRzH","outline_menu.md":"DWqp5-la","outline_member.md":"BexRW3eM","monitoring_helpers_deprecated.md":"9K5dPJOv","outline_tip.md":"C8IJ1ePp","outline_remove-youngcart.md":"CPWR-XGF","outline_upgrade.md":"DFP_tdvi","outline_index.md":"3eTuzhyP","monitoring_info.md":"C2KL40O4","outline_install.md":"DpKzarmm","outline_theme_skin.md":"B5z32OeW"}
