{"monitoring_info.md":"BGLBDE5a","outline_theme_skin.md":"BWOJpVG_","monitoring_helpers_deprecated.md":"cjJgLPMn","outline_member.md":"CMfxiXhC","outline_point.md":"E53G5R8o","outline_board.md":"D0gpPmzK","outline_index.md":"BUth8ySX","outline_privacy.md":"B07dkMR_","outline_config.md":"DjoU2vNb","outline_remove-youngcart.md":"B7jStbKm","outline_theme-and-skin.md":"CKhh0D_f","outline_upgrade.md":"BlzTFWBN","outline_menu.md":"1dZMeZ2C","outline_update.md":"DsVr1Fld","outline_basic-config.md":"25LD5JLN","outline_tip.md":"Cv1jHAWT","index.md":"4wTXjhu9","outline_install.md":"CexkO8HZ","monitoring_process.md":"DYLRq3KI"}
