{"outline_board.md":"BC-OykHZ","monitoring_info.md":"BXMtR1uM","outline_index.md":"D0hnsgNU","monitoring_process.md":"CJyhmBPN","outline_point.md":"DiD05yGb","outline_menu.md":"BX6xbfCv","outline_privacy.md":"ldVZLAE5","outline_tip.md":"DcqjDcRY","outline_upgrade.md":"CRo06_I_","outline_theme_skin.md":"Cp2ff0Wp","outline_basic-config.md":"C9mZWgdc","outline_member.md":"5QMehnpX","outline_install.md":"hRhN79ae","outline_config.md":"B8TSah_D","outline_update.md":"BF_wmIdm","index.md":"BoRHaPXb","monitoring_helpers_deprecated.md":"C-i3lAA7","outline_theme-and-skin.md":"DKVya3Km","outline_remove-youngcart.md":"Ct8CGi3K"}
