{"outline_board.md":"CmIs46N-","monitoring_info.md":"D_DIrO75","outline_config.md":"CgOfWyN1","outline_index.md":"CXeNQs6M","outline_theme-and-skin.md":"D9oqaPF2","outline_basic-config.md":"Dccffgk_","outline_theme_skin.md":"jyX8onGh","outline_upgrade.md":"DDDsW6HE","outline_member.md":"B8V9l5vx","outline_install.md":"hHadXbOu","monitoring_helpers_deprecated.md":"r89ctvud","outline_point.md":"CRRuu79U","outline_menu.md":"B45UlGct","monitoring_process.md":"BkkHlMaf","index.md":"Xmdru-5z","outline_remove-youngcart.md":"DgL8BhBz","outline_tip.md":"HkaXmq24","outline_privacy.md":"Cd9TzX1W","outline_update.md":"CLZUOT_a"}
