{"outline_theme_skin.md":"chZ_3Tjl","outline_board.md":"Br3ULDCx","outline_member.md":"CZK-ffxt","outline_menu.md":"DffPycDY","outline_basic-config.md":"yfAX3OCF","outline_update.md":"CsKZVmUH","monitoring_helpers_deprecated.md":"DwWNha00","monitoring_info.md":"Bj5519gm","monitoring_process.md":"B9KICnwV","outline_index.md":"Dh_Aio-5","outline_remove-youngcart.md":"CDRlPZDl","outline_point.md":"BwyhtF1j","outline_theme-and-skin.md":"tBnhUpJl","outline_upgrade.md":"1Jb4pNTv","outline_config.md":"Bxg8kIPq","outline_install.md":"ZdQpqSmN","index.md":"nAZNelWU","outline_privacy.md":"CHQLDLTG","outline_tip.md":"BzMzmbRQ"}
