{"monitoring_info.md":"BjaxNoc9","monitoring_process.md":"DKrDsYJd","outline_tip.md":"naMCI9Ea","outline_upgrade.md":"CK9nkKDp","monitoring_helpers_deprecated.md":"CrCvf3FO","outline_board.md":"DvRw2pQE","outline_point.md":"BeXwLsWa","outline_menu.md":"BzJ8Huac","outline_theme-and-skin.md":"D5uLTxcH","outline_config.md":"ULbAZBU9","outline_update.md":"DqPhng3-","outline_privacy.md":"CPcQHUWj","outline_basic-config.md":"DVXI1JFF","outline_index.md":"O7rPL1jX","outline_member.md":"BZlMWToP","outline_remove-youngcart.md":"7N8SsfVq","outline_install.md":"BVZ7ET6N","index.md":"BZvhj_4U","outline_theme_skin.md":"CDs9ceBJ"}
