{"monitoring_process.md":"BWnv4C49","outline_point.md":"Cs3oTw-x","outline_theme_skin.md":"DnP6MKPl","outline_index.md":"DlW7SY5I","index.md":"DpAu54JX","outline_board.md":"DfUrq_52","monitoring_helpers_deprecated.md":"DUH4aHqn","outline_basic-config.md":"BnlYhJaC","outline_config.md":"CCn3-RMk","outline_theme-and-skin.md":"CMu5IS_b","outline_menu.md":"CtPy6bg4","outline_tip.md":"CEjG2vY3","outline_install.md":"G8KHwEPc","monitoring_info.md":"qnSisoR9","outline_member.md":"BmA_zaAW","outline_privacy.md":"C0n9gg22","outline_update.md":"BGWv0ifl","outline_remove-youngcart.md":"ChJYLKEy","outline_upgrade.md":"B2t2zCJZ"}
