{"outline_menu.md":"Dw795AWv","index.md":"B3EzQFeB","monitoring_helpers_deprecated.md":"DutkfiBm","monitoring_process.md":"BS3JuQO3","outline_config.md":"Dtbo1y-9","outline_index.md":"iauCekUQ","outline_point.md":"BKNWz4HL","outline_theme_skin.md":"DiX-3MzE","outline_install.md":"Dl6DfD73","outline_member.md":"Rtk5T_Qg","outline_upgrade.md":"CimrvERs","outline_tip.md":"m3ncOVPR","outline_theme-and-skin.md":"B5OXbpjr","outline_update.md":"CutrqRqm","outline_privacy.md":"BWTDh0YW","outline_board.md":"g1eEwdt7","outline_basic-config.md":"CQ5zK-L0","monitoring_info.md":"B7J1B0Yc","outline_remove-youngcart.md":"IgF92F_l"}
