{"monitoring_helpers_deprecated.md":"DobGSuCx","monitoring_info.md":"Zi3mTUjr","outline_upgrade.md":"Dp01l_jp","index.md":"WF6LPs1O","outline_privacy.md":"COierKTM","outline_point.md":"rBERZk42","monitoring_process.md":"kkKv0L_U","outline_theme-and-skin.md":"DkUqvJkw","outline_basic-config.md":"D0Y-PVBo","outline_board.md":"D3KqGLU5","outline_update.md":"DbNUWod9","outline_index.md":"BslcOr2E","outline_theme_skin.md":"CVHizSpR","outline_menu.md":"B-TcH5yp","outline_member.md":"Bd9xsuNt","outline_config.md":"CM4IrmUC","outline_tip.md":"aB_En9yx","outline_remove-youngcart.md":"CHTNlFpw","outline_install.md":"BpXAcRWl"}
