{"monitoring_info.md":"mwtxTfeM","outline_board.md":"DWFqBRKU","outline_menu.md":"CHsRTMZ0","outline_basic-config.md":"D7ayzg1S","outline_privacy.md":"5FMWBNrZ","outline_theme-and-skin.md":"C_94uB5G","outline_point.md":"BLrWfpFd","outline_theme_skin.md":"DkdLNYXG","outline_remove-youngcart.md":"0nQhGHjK","outline_tip.md":"WS65Kjor","outline_config.md":"RD-VrtpD","index.md":"D2jSEOjM","outline_update.md":"DnWguS60","outline_index.md":"BfZ9lU1S","monitoring_process.md":"HyhHRPI7","outline_upgrade.md":"BGJ_xQYh","monitoring_helpers_deprecated.md":"BxenLCey","outline_member.md":"CR3ns2Kg","outline_install.md":"DdENhqG7"}
