{"outline_member.md":"C_0TUMu0","outline_menu.md":"C07UnbXr","index.md":"BBfjFOB9","monitoring_process.md":"DVPkk1Xy","outline_basic-config.md":"CRaDPjx5","outline_install.md":"Cpu7yX_r","outline_index.md":"Bi1qB8eX","outline_theme_skin.md":"C5aspPOk","outline_board.md":"M4Uxn3gE","outline_theme-and-skin.md":"C9mR-YCK","outline_point.md":"C-6GuIlq","outline_config.md":"Ds1jFkS7","outline_tip.md":"DglH8zvl","outline_upgrade.md":"DC9Dsfl1","outline_remove-youngcart.md":"CjN8cCVM","monitoring_info.md":"CN7TBv-7","monitoring_helpers_deprecated.md":"BwpAJkAe","outline_privacy.md":"CYwbHUyH","outline_update.md":"D7nVRoZ7"}
