{"index.md":"Cxk92ck4","outline_theme-and-skin.md":"BMZIFpJ7","outline_theme_skin.md":"DCGg5lh8","outline_remove-youngcart.md":"DMG13u6A","outline_update.md":"CWvojQe0","outline_tip.md":"C8ioJBIK","outline_member.md":"CAfrcVCq","outline_basic-config.md":"BC1ULodi","monitoring_process.md":"CMD0rG0s","outline_point.md":"BCncOcUw","outline_install.md":"DWj9jYYZ","outline_menu.md":"MC6ToqNX","outline_upgrade.md":"AkeNCoE7","outline_board.md":"BVRCXxan","monitoring_info.md":"CuhgWjg4","outline_index.md":"BATObiM9","outline_privacy.md":"DValB_Fk","outline_config.md":"uB6EEDsf","monitoring_helpers_deprecated.md":"4OlamNuQ"}
