{"monitoring_helpers_deprecated.md":"D2fUgk6C","outline_config.md":"CsbjjbEz","outline_install.md":"sS-c0g_4","monitoring_process.md":"D8-lCt44","outline_theme_skin.md":"DPT3Zf31","outline_remove-youngcart.md":"BFn57ZZu","outline_privacy.md":"DdVkyqKf","outline_index.md":"CyiqWDhO","outline_theme-and-skin.md":"Ba0D4dp9","outline_point.md":"Dm2osuA0","index.md":"BbZJYOR-","outline_board.md":"Cv9--qFc","outline_member.md":"DmjHjOFw","outline_update.md":"C2AO21rf","monitoring_info.md":"Bh0HWTSF","outline_tip.md":"FziFdMVi","outline_upgrade.md":"BQA-MpqZ","outline_basic-config.md":"DTyjRRbd","outline_menu.md":"Bi8tgE6a"}
