{"outline_menu.md":"DHYA0OaS","outline_install.md":"CNPKwuQF","outline_index.md":"BiLmCgfO","monitoring_helpers_deprecated.md":"B6XX_lk8","outline_point.md":"CcQi2wYc","outline_member.md":"Dr_uWUfj","outline_tip.md":"BYD3OC4_","outline_board.md":"CU9YroG-","index.md":"CWJxKm5X","outline_privacy.md":"B2Y0nYoe","outline_theme_skin.md":"BtrZB0y-","monitoring_info.md":"BMSN96xq","outline_config.md":"C9JIsKMw","outline_upgrade.md":"9ZjsDLPI","outline_theme-and-skin.md":"FkLCRJeZ","outline_remove-youngcart.md":"CCCPkKmi","outline_update.md":"vvwrR5iE","outline_basic-config.md":"BtCVyYDj","monitoring_process.md":"CSQZawI6"}
