{"outline_menu.md":"AYpjkYkq","index.md":"B7NIyiiw","monitoring_process.md":"LQqPRi2W","outline_basic-config.md":"BqQJk2f4","outline_point.md":"CUtT4vCZ","monitoring_helpers_deprecated.md":"BPadqOse","outline_board.md":"BXwCWYVT","outline_theme_skin.md":"MlUXGjgJ","outline_theme-and-skin.md":"B3Nsl8hy","outline_privacy.md":"I_4_M1oo","outline_update.md":"DittqMox","outline_remove-youngcart.md":"DDAPzxMN","outline_index.md":"6rEkOoCI","outline_install.md":"C3v2aHac","outline_config.md":"DHFqkM8C","outline_upgrade.md":"Bzmj0IsT","outline_tip.md":"B5Ggr6s6","monitoring_info.md":"Du0P0p7N","outline_member.md":"DC7J6szL"}
