{"monitoring_process.md":"Cs7pDRAR","monitoring_helpers_deprecated.md":"BY-So4gK","outline_index.md":"BmPA4dIh","outline_board.md":"aqyDTBf2","outline_config.md":"BNLaT73z","outline_menu.md":"CUXA7duK","outline_upgrade.md":"C4KoM1UK","outline_member.md":"CibSURqt","outline_tip.md":"PQ6snCmD","outline_basic-config.md":"CzCw1d6o","outline_theme_skin.md":"DDziaM5k","outline_theme-and-skin.md":"CO-pRYQF","outline_remove-youngcart.md":"C0Xaw0lG","index.md":"DalyXpTG","monitoring_info.md":"DRIvmI1M","outline_install.md":"Bglgm6Xs","outline_update.md":"CnN7ynnt","outline_privacy.md":"Bzl-WzH6","outline_point.md":"BUkPwRp-"}
