{"outline_point.md":"Bth0rSa6","outline_install.md":"B_z3OfVt","outline_upgrade.md":"5xjbjncJ","index.md":"B6HcGKl2","outline_menu.md":"BlRo7EE3","outline_remove-youngcart.md":"Bd3XGTyS","monitoring_process.md":"8FrMT6O2","outline_board.md":"CXu8pSfv","outline_tip.md":"DpV6InU3","outline_config.md":"BHmm3cpN","outline_basic-config.md":"LuHJmL8G","monitoring_helpers_deprecated.md":"CowO6ti6","outline_theme-and-skin.md":"DttvYc8h","outline_member.md":"Du4y2DI5","outline_index.md":"DrKoWG7R","monitoring_info.md":"C6ka5tQM","outline_theme_skin.md":"BI9j4z39","outline_privacy.md":"DqrQ-dBx","outline_update.md":"Dh6C7OcK"}
