{"outline_theme_skin.md":"CW7AZRww","outline_install.md":"BicFu3NH","outline_upgrade.md":"CbUTrKe-","outline_board.md":"C9bP6pex","outline_tip.md":"Bel_tas0","monitoring_info.md":"DeB-cQof","index.md":"CTKKnoTR","outline_menu.md":"BCtHiYgA","outline_basic-config.md":"DDHE69DY","outline_index.md":"BnaN8kXN","outline_theme-and-skin.md":"Czuejoft","outline_point.md":"CeDByF1Z","outline_update.md":"CflunXpl","monitoring_helpers_deprecated.md":"CPnIyDSn","outline_config.md":"BzCGc9QC","outline_remove-youngcart.md":"CGltTlh7","outline_privacy.md":"CRGne_Dt","outline_member.md":"C-TL5-41","monitoring_process.md":"hz334j9d"}
