{"outline_update.md":"DlFU7lE9","outline_privacy.md":"DSqA8RHM","outline_upgrade.md":"CoDy0KVe","outline_config.md":"77Kduglv","outline_point.md":"Di6jZfcH","outline_tip.md":"BKnFulCh","outline_theme-and-skin.md":"DSOiiYcQ","outline_basic-config.md":"BRkehEWa","monitoring_process.md":"ez_sCBqz","monitoring_helpers_deprecated.md":"DxDclV3U","outline_board.md":"_2dVh-Uq","outline_menu.md":"DyuQeIlA","outline_install.md":"CMYqN8KP","outline_index.md":"D_57RAZK","outline_theme_skin.md":"JfZ1rNPa","outline_remove-youngcart.md":"aoBPOLgK","index.md":"B3G2uTQX","outline_member.md":"u59kuDsq","monitoring_info.md":"CvHiK2xk"}
