{"monitoring_helpers_deprecated.md":"4wYjPVYM","outline_menu.md":"zQsFV9QL","monitoring_process.md":"CoQlTB44","outline_index.md":"BYfJHGuA","outline_install.md":"C7svIch6","index.md":"CiIipTaL","outline_privacy.md":"BMKFxKcn","outline_basic-config.md":"VhYPpAyh","outline_point.md":"Bgy3XP69","outline_theme-and-skin.md":"tcyk1uZ_","outline_config.md":"CQ7dL0Iq","outline_theme_skin.md":"CGTpEJU_","outline_update.md":"D47V-4Sk","outline_tip.md":"D6T35kec","outline_upgrade.md":"BVIyH85f","outline_board.md":"g1ZPOLqv","monitoring_info.md":"qZsIsJrB","outline_member.md":"Cq5uPZFV","outline_remove-youngcart.md":"CURKhrFD"}
