{"outline_privacy.md":"JhUviiW7","outline_menu.md":"C5ZjzQKd","monitoring_helpers_deprecated.md":"2ZOfKXYU","outline_index.md":"CfH-CXJd","outline_board.md":"CFwOf8AJ","outline_member.md":"Cdrphlw2","outline_install.md":"B396Ruqq","outline_config.md":"DQREcTKP","monitoring_info.md":"C1_NU_wj","outline_theme-and-skin.md":"BLPtqbKU","outline_tip.md":"SqLSbR--","outline_update.md":"OGisqrrj","index.md":"D2Z4iFYU","outline_remove-youngcart.md":"DuDNNLIs","outline_theme_skin.md":"BEqjLFxv","outline_basic-config.md":"Cae_4Mtm","outline_upgrade.md":"Cya2Gj8i","monitoring_process.md":"CkSxHBO4","outline_point.md":"BZe1Ebcc"}
