{"outline_config.md":"Br0bt8YX","monitoring_process.md":"7a-q-uUX","outline_member.md":"B_cw6tw5","outline_tip.md":"BBPHC3Ew","outline_privacy.md":"BkKWAZYD","outline_theme-and-skin.md":"CI033byi","outline_theme_skin.md":"CnxvelA3","outline_basic-config.md":"CYXcMIbR","outline_install.md":"D2vu3SRR","outline_point.md":"CI0pxA-A","outline_upgrade.md":"BXm2X8ij","index.md":"BXpt6BlR","outline_menu.md":"D1hS7P2B","outline_update.md":"Cx6vOqCT","monitoring_info.md":"qi2GUwpl","outline_index.md":"DuYV7Inz","outline_board.md":"J1JGi_uj","monitoring_helpers_deprecated.md":"BSrY2BZP","outline_remove-youngcart.md":"CkkucGNj"}
