{"outline_install.md":"DR1WoyIu","outline_board.md":"BMEAJtoq","outline_basic-config.md":"CgKGSH1m","index.md":"D5BehsL0","outline_menu.md":"Cr6AW2oB","outline_member.md":"C-s8njBa","outline_config.md":"-URffQmb","outline_index.md":"DDD81YKR","outline_privacy.md":"DV5N9DWu","monitoring_info.md":"CXHCzHOe","monitoring_process.md":"Bx3e3P15","outline_tip.md":"DM6IWOl1","outline_point.md":"CJk9p8pX","outline_remove-youngcart.md":"BB6oaCyS","outline_theme_skin.md":"DmEGhFBs","outline_upgrade.md":"C9hau9j2","outline_theme-and-skin.md":"CvOHZuDZ","outline_update.md":"Bhk3uVho","monitoring_helpers_deprecated.md":"DbSx72z8"}
