{"index.md":"DaJANaln","monitoring_info.md":"CU8kyxNA","monitoring_process.md":"lhTMPuT3","outline_index.md":"DrpDAiIb","outline_install.md":"B3e1ivmb","outline_board.md":"FDdArbwL","outline_basic-config.md":"VX0BG4_Q","outline_config.md":"BBbUPt42","outline_update.md":"De8XOj2I","outline_tip.md":"nC7XPeae","outline_remove-youngcart.md":"eLuoS3yE","outline_theme-and-skin.md":"Chx9as42","outline_point.md":"sfL0niip","outline_menu.md":"5YxODu0G","outline_member.md":"KVqCqay7","outline_theme_skin.md":"B-3Di3s2","outline_privacy.md":"DDz-UrWA","outline_upgrade.md":"-uQM37gu","monitoring_helpers_deprecated.md":"Dz-Q6XpB"}
