{"outline_theme-and-skin.md":"c4JOKVa-","outline_theme_skin.md":"Cml1GmZx","outline_update.md":"DHeg8hmb","monitoring_helpers_deprecated.md":"CpgTHcSa","outline_privacy.md":"MU2cPHJI","outline_basic-config.md":"BhoxigMW","monitoring_process.md":"BjbxaeFp","index.md":"TDkBXgFZ","outline_config.md":"BWqxkRcn","outline_board.md":"B6tRySpy","outline_point.md":"BMAOYqRO","outline_member.md":"DeO52e54","outline_install.md":"DWeiWJYR","outline_tip.md":"C48YJ6mf","outline_upgrade.md":"C7gnw8dE","outline_remove-youngcart.md":"4ikph6MI","monitoring_info.md":"ixhEsbCO","outline_index.md":"BfXQVIQx","outline_menu.md":"D8j2RU_o"}
