{"outline_index.md":"raFBwOfD","outline_tip.md":"Djm8L3A2","outline_privacy.md":"zItRjwuZ","outline_menu.md":"BIR7umSZ","outline_theme_skin.md":"BIbpVzC9","outline_point.md":"B6-szdwC","outline_board.md":"xY5naefD","monitoring_helpers_deprecated.md":"Cg0xcElk","monitoring_process.md":"DZ6Q0zwA","outline_upgrade.md":"f6Wr_OFx","outline_remove-youngcart.md":"Dug7D5id","monitoring_info.md":"DPl3P9yM","outline_member.md":"BJ1PX1Ur","outline_basic-config.md":"Ds0ww1vs","outline_update.md":"BM1m1a52","outline_theme-and-skin.md":"BRKnBo6_","index.md":"DPXA39JZ","outline_install.md":"CrfraI2p","outline_config.md":"CaHUGiQH"}
