{"outline_theme-and-skin.md":"DR6z8fam","outline_board.md":"CgCUMCLe","monitoring_helpers_deprecated.md":"BhhTC6Jq","outline_update.md":"DCtCi78a","outline_index.md":"DhfzUtby","outline_point.md":"CLgm98mJ","outline_install.md":"-ArTk0Yo","outline_member.md":"2mVwCk6f","outline_privacy.md":"r9LFliGU","outline_tip.md":"y8gGaU1y","outline_theme_skin.md":"C_31tvbU","monitoring_process.md":"BDdgAoC7","monitoring_info.md":"C_xCdVYZ","outline_config.md":"CPms4cu3","outline_remove-youngcart.md":"iJoGaa9u","outline_basic-config.md":"7ehiOmeW","index.md":"BOZfIk-9","outline_menu.md":"B14NXXQ4","outline_upgrade.md":"BbAGAfIw"}
