{"outline_theme_skin.md":"BVuDEJEN","outline_install.md":"K6N3dQT_","outline_member.md":"2n1s3ajP","outline_menu.md":"BYDZ5Irl","outline_point.md":"nrrx3t_6","monitoring_helpers_deprecated.md":"BiNXybp1","monitoring_process.md":"DtBWGnJ0","outline_board.md":"C00_xHo1","outline_basic-config.md":"Dqrkc8RM","monitoring_info.md":"njceueX9","outline_upgrade.md":"BDGYyOw2","outline_config.md":"DqvNVoxT","outline_index.md":"CaZghX9W","outline_update.md":"Cu9wq-c7","outline_theme-and-skin.md":"C3ZSEzgR","outline_tip.md":"CwoZjbj_","index.md":"CApSP971","outline_remove-youngcart.md":"BR0fxEua","outline_privacy.md":"DP1PXfQ-"}
