{"outline_member.md":"BI2BvrSm","index.md":"BFw8kDoR","outline_board.md":"Do4NvgBA","outline_theme-and-skin.md":"IkBNUpm9","outline_remove-youngcart.md":"DcSbCXQa","outline_tip.md":"DpyItcXI","outline_theme_skin.md":"CvHppCp4","outline_upgrade.md":"BE4m6C68","monitoring_info.md":"Cu2kA9Q3","outline_config.md":"3aqoQyJZ","outline_install.md":"CoVEmZkj","monitoring_process.md":"OOCU0jCk","outline_privacy.md":"B0ihtuzy","outline_point.md":"BdRVIM6z","outline_index.md":"SHqNu_Jv","outline_basic-config.md":"m4ybcW1-","outline_menu.md":"I7MJsruG","outline_update.md":"n0pGvaLd","monitoring_helpers_deprecated.md":"DNhxcUAE"}
