{"outline_basic-config.md":"DyaiiICX","outline_member.md":"BiptciBE","outline_point.md":"DA6TIWrD","outline_board.md":"RbzZfC9o","index.md":"CoKg1Vdp","outline_config.md":"B2_cF_KD","outline_privacy.md":"Ckhr0D-N","outline_remove-youngcart.md":"D7e3bgsk","monitoring_process.md":"BQS_tczL","outline_tip.md":"CrPEjJWV","outline_update.md":"DOyp8b6u","outline_theme-and-skin.md":"D-ArYnGK","outline_upgrade.md":"CDMYlaKm","outline_menu.md":"DqAg_TZv","outline_theme_skin.md":"Dl7geapu","outline_index.md":"D34gPIkM","outline_install.md":"Euo7qj6i","monitoring_info.md":"D9ea30-j","monitoring_helpers_deprecated.md":"D9achB7J"}
