{"outline_theme_skin.md":"CwvucV2s","outline_tip.md":"D8Os5GTI","outline_upgrade.md":"Q8iEAx4k","outline_update.md":"DhIcwuQY","outline_point.md":"Xz04EzVc","outline_basic-config.md":"P8cXcClH","monitoring_process.md":"B5JRZvjc","outline_theme-and-skin.md":"qGtWC6Iz","outline_menu.md":"BaXbb5-N","monitoring_helpers_deprecated.md":"ChpYnbuj","index.md":"CzmRquB1","outline_install.md":"CBnmbwg0","outline_index.md":"C61u9aB9","monitoring_info.md":"B_8U-Vex","outline_remove-youngcart.md":"Gl5iD4x3","outline_privacy.md":"pantoFC1","outline_board.md":"DyH5OSga","outline_config.md":"BqEh4nng","outline_member.md":"DcPwrK9-"}
