{"outline_basic-config.md":"rp3jIG4R","outline_install.md":"Cy6oSYQJ","outline_config.md":"UV6klgrB","monitoring_process.md":"BptqSJzP","outline_board.md":"DtBtGu_M","outline_theme_skin.md":"DirwQXB2","outline_menu.md":"C7CKM-ID","index.md":"CqGBm7D2","monitoring_helpers_deprecated.md":"D4B3fgHE","outline_upgrade.md":"BhJEP1bI","outline_point.md":"DiAHBlTs","outline_privacy.md":"CR1ekrVS","outline_theme-and-skin.md":"_DhV2jos","outline_tip.md":"B8w-AAN4","outline_index.md":"Cjfub0BP","outline_member.md":"Du4rs-mR","monitoring_info.md":"h9uNFNyW","outline_remove-youngcart.md":"MZwaqgcv","outline_update.md":"3kWg5pa_"}
