{"index.md":"Dw9nXXOU","outline_member.md":"DPy9hqgd","outline_tip.md":"CsLklJEY","outline_index.md":"BnRv74Jd","outline_menu.md":"DOJxeZjW","outline_config.md":"BA9ivdtT","outline_privacy.md":"BwgLhXLP","outline_basic-config.md":"B6o5wJXG","outline_point.md":"B_Y_VJuT","outline_board.md":"BhjJZOIY","outline_theme_skin.md":"Cug0_ryX","outline_update.md":"CHrIxdss","outline_remove-youngcart.md":"Ct7lWscs","monitoring_info.md":"B0DM-VT-","outline_upgrade.md":"Ivv2aoOm","outline_theme-and-skin.md":"MMHVss_p","monitoring_helpers_deprecated.md":"C9OezRiU","outline_install.md":"Dcromhfi","monitoring_process.md":"C-IkqqXp"}
