{"index.md":"GzGiRE5p","outline_theme-and-skin.md":"WR9lNOPj","outline_basic-config.md":"yVfpqubR","monitoring_info.md":"DKIQNJIz","outline_board.md":"Dddk2zBg","outline_tip.md":"D18IepYz","outline_point.md":"Bf53jNlf","outline_member.md":"DhQ9eT4N","outline_config.md":"CD5pRKpu","monitoring_helpers_deprecated.md":"Crx9QUNO","outline_update.md":"Any8l6EA","monitoring_process.md":"D2tL5hQo","outline_upgrade.md":"sbEWys42","outline_menu.md":"C8b08DPi","outline_index.md":"Cs_l6bZT","outline_theme_skin.md":"B0l6M4zG","outline_remove-youngcart.md":"BVjDQxOD","outline_privacy.md":"C0y9zwUR","outline_install.md":"BZSRDITy"}
