{"monitoring_info.md":"B3yU-9Cd","outline_theme-and-skin.md":"7Ft5SfRA","index.md":"0ZhsWnTi","outline_menu.md":"DcklfHpH","outline_upgrade.md":"D7t_6ozW","monitoring_helpers_deprecated.md":"B1vUtZVL","outline_board.md":"Czss3kL2","outline_tip.md":"DjHSm3kQ","outline_index.md":"Dgmfvrx9","outline_remove-youngcart.md":"6gUi90OT","outline_privacy.md":"Z5dRLDN5","outline_config.md":"BvLrsXLL","outline_theme_skin.md":"CCL-R9IB","outline_basic-config.md":"CAmkfshp","outline_update.md":"g67lVsxf","monitoring_process.md":"D_4uMv9G","outline_point.md":"DDKF7RNP","outline_member.md":"C5jCoAzR","outline_install.md":"BEvvmIR_"}
