{"outline_member.md":"Ca__qVHa","outline_config.md":"Cyj8HKaI","outline_remove-youngcart.md":"CJ4ptuWh","monitoring_process.md":"DMm2N5tr","index.md":"BqFWbzLL","outline_point.md":"ChR0bRC1","monitoring_helpers_deprecated.md":"MZeuc7dr","outline_theme-and-skin.md":"D834OhjB","outline_upgrade.md":"dSEGqteQ","outline_basic-config.md":"Ctkau260","outline_update.md":"cckz5RUe","outline_theme_skin.md":"B5sToeq_","outline_tip.md":"BK5A69z1","outline_menu.md":"C71bQiu1","outline_privacy.md":"DIz9GmwI","outline_install.md":"p-ofOE1c","monitoring_info.md":"BHgBre_a","outline_board.md":"CbVonbAA","outline_index.md":"Ds0CsPQY"}
