{"outline_menu.md":"CjZF2B2M","monitoring_helpers_deprecated.md":"qh0TJoIi","outline_install.md":"DuiTaXlf","index.md":"Cw3DBrhR","outline_basic-config.md":"By0ylzFB","outline_member.md":"BDEpcb7C","outline_index.md":"DK-7JTS0","outline_privacy.md":"DimJRAin","outline_point.md":"DvKVbL9N","monitoring_process.md":"COOzDo6e","outline_tip.md":"xsv0aFR-","outline_config.md":"WToyhRA2","outline_update.md":"C1SLOwFh","outline_theme-and-skin.md":"CvJYd5sb","outline_upgrade.md":"C1wGBa1P","outline_remove-youngcart.md":"WCuNH5nV","monitoring_info.md":"arAeiuCZ","outline_theme_skin.md":"DtC0EPn7","outline_board.md":"DOpgukzK"}
