{"outline_theme_skin.md":"DnUMZYS3","outline_upgrade.md":"r3EcYXlw","outline_update.md":"ntOLZ8LU","outline_tip.md":"CkdE9irG","outline_install.md":"B4m3eOIN","outline_remove-youngcart.md":"BP6eX-79","outline_index.md":"0qNwlAWZ","outline_point.md":"lFRZQ6tb","outline_member.md":"DzNTmnLR","index.md":"DNtpcTmh","monitoring_helpers_deprecated.md":"zKQGekVx","outline_board.md":"6So2u-wi","monitoring_info.md":"CftlbSc9","outline_menu.md":"BYlVRt0a","outline_theme-and-skin.md":"z4J5Yn7y","outline_basic-config.md":"Bh5d9_CO","monitoring_process.md":"NTvFxZVL","outline_config.md":"CEnMY-uk","outline_privacy.md":"B_NyySdK"}
