{"index.md":"DfqGc5wb","outline_upgrade.md":"iyPsJza-","outline_index.md":"p8n4d_So","monitoring_helpers_deprecated.md":"8xvM5laL","outline_point.md":"B060HCBT","outline_theme_skin.md":"CPwwt4Xt","outline_remove-youngcart.md":"CekexJUB","outline_tip.md":"C_17wnq9","outline_board.md":"DG7rQ22m","outline_config.md":"cpTtldWX","outline_member.md":"CQtm7jP-","outline_theme-and-skin.md":"zxkQOKAr","outline_update.md":"CC-aIbmQ","monitoring_process.md":"C4nPRs_W","monitoring_info.md":"w3t0on3O","outline_basic-config.md":"DCekG9Hv","outline_menu.md":"BN1JBaWa","outline_install.md":"BLSkD_VW","outline_privacy.md":"B1QJQBg6"}
