{"monitoring_process.md":"B8Y3aPSI","outline_theme_skin.md":"GhQAUSYJ","outline_theme-and-skin.md":"CljaRlud","outline_member.md":"BSk9v5RQ","outline_upgrade.md":"DqkJxEal","outline_board.md":"DBUrUI6I","outline_config.md":"D9MrdOMe","index.md":"EwRqAiGb","outline_privacy.md":"CUGuux4A","monitoring_info.md":"BIVEdTMi","outline_basic-config.md":"C8MENPFI","outline_tip.md":"Cize9W7A","outline_install.md":"DIYWY9TR","outline_index.md":"B-iqp2wO","monitoring_helpers_deprecated.md":"xvGi95U2","outline_point.md":"CirifSCZ","outline_remove-youngcart.md":"cINMzNUm","outline_menu.md":"CAI1PsIc","outline_update.md":"BuYfyHaS"}
