{"outline_tip.md":"DTi8irTQ","outline_point.md":"D-Geg07z","outline_upgrade.md":"D4RRnZZZ","index.md":"yHhAdl_s","monitoring_helpers_deprecated.md":"B9FXXzu2","outline_theme_skin.md":"BStxFX8R","outline_theme-and-skin.md":"NUcq3-dJ","outline_config.md":"Cz2HFTwe","monitoring_info.md":"CDw18LQr","outline_member.md":"C-Ltvp_Y","outline_update.md":"DtRIWzNt","outline_remove-youngcart.md":"Dz87Qibs","outline_install.md":"CPEnbpRm","outline_index.md":"LaE88PVl","outline_basic-config.md":"BQXlhUDG","outline_board.md":"BTXqfd6M","monitoring_process.md":"BFNyNR-C","outline_menu.md":"oYUhD1lx","outline_privacy.md":"D6ltpmvJ"}
