{"outline_board.md":"JQauSpCv","outline_privacy.md":"C44zLNNq","outline_theme-and-skin.md":"C_0Vstxf","outline_theme_skin.md":"91aMTk9q","outline_config.md":"Dbz2y5cz","outline_tip.md":"B6pn3jeH","monitoring_helpers_deprecated.md":"6RK2k6U6","outline_basic-config.md":"CHMMm-R-","outline_menu.md":"DyVaTidz","outline_index.md":"B_gxI50z","outline_update.md":"DduxEeAQ","monitoring_info.md":"CfJyOeuV","outline_upgrade.md":"D-a8Msbc","outline_remove-youngcart.md":"gsrcwDVU","outline_member.md":"UnyH9wxP","index.md":"PVPaCmMf","monitoring_process.md":"BCfmWe_w","outline_point.md":"DEV85hVe","outline_install.md":"EMV43Nci"}
