{"monitoring_helpers_deprecated.md":"BwSF1Qtf","outline_theme-and-skin.md":"BfafPy1y","outline_update.md":"BR2ZZqqg","outline_theme_skin.md":"D4_rRJXm","outline_config.md":"e0Tx6stk","outline_basic-config.md":"DZp9v9GE","outline_install.md":"C2QH-SQR","outline_board.md":"Cef7K4I9","outline_member.md":"DkfFIXLK","index.md":"BQ7eV2P7","outline_tip.md":"i2nPDBAs","outline_upgrade.md":"B6abERBm","monitoring_process.md":"BfV5CSb_","monitoring_info.md":"QXROQ0rq","outline_index.md":"FqtSfHi4","outline_privacy.md":"BEhs6_wj","outline_menu.md":"CE0jiIoE","outline_remove-youngcart.md":"CuNXmNgy","outline_point.md":"C0K6p3uP"}
