{"outline_config.md":"C08yX4v6","outline_board.md":"By_d5L-g","outline_install.md":"fJns7Vs7","outline_privacy.md":"Cwi6aXMQ","monitoring_info.md":"0w8DlK1n","outline_theme_skin.md":"aI9Lkq3J","outline_remove-youngcart.md":"CSTGaZI8","outline_menu.md":"Dn4Yow9T","outline_theme-and-skin.md":"D_NrA1qc","outline_upgrade.md":"DHYa20mA","outline_point.md":"Dg3yhJYL","monitoring_process.md":"DfTlXy4e","monitoring_helpers_deprecated.md":"C1c5FmdP","outline_update.md":"DmqLwNI2","outline_tip.md":"D274qV03","outline_basic-config.md":"DKzsqBEj","outline_index.md":"XPtwL2p3","index.md":"DYunmqKr","outline_member.md":"2BlIXBtN"}
